README.rst
setup.py
django_k8s/__init__.py
django_k8s/models.py
django_k8s/settings.py
django_k8s/tests.py
django_k8s/urls.py
django_k8s/version.py
django_k8s/wsgi.py
django_k8s.egg-info/PKG-INFO
django_k8s.egg-info/SOURCES.txt
django_k8s.egg-info/dependency_links.txt
django_k8s.egg-info/top_level.txt
django_k8s/cache/__init__.py
django_k8s/cache/backends/__init__.py
django_k8s/cache/backends/memcached.py
django_k8s/management/__init__.py
django_k8s/management/commands/__init__.py
django_k8s/management/commands/checkmigrations.py