Metadata-Version: 1.1
Name: django-k8s
Version: 0.2.9
Summary: Integration between Django and Kubernetes.
Home-page: http://github.com/btimby/django-k8s/
Author: Ben Timby
Author-email: btimby@gmail.com
License: MIT
Platform: UNKNOWN
Classifier: Development Status :: 4 - Beta
Classifier: Intended Audience :: Developers
Classifier: Operating System :: OS Independent
Classifier: Programming Language :: Python :: 2
Classifier: Programming Language :: Python :: 3
Classifier: Topic :: Software Development :: Libraries :: Python Modules
